getpass_asterisk/__init__.py
getpass_asterisk/getpass_asterisk.py
getpass_asterisk-1.0.1.dist-info/LICENSE
getpass_asterisk-1.0.1.dist-info/METADATA
getpass_asterisk-1.0.1.dist-info/WHEEL
getpass_asterisk-1.0.1.dist-info/top_level.txt
getpass_asterisk-1.0.1.dist-info/RECORD
