Metadata-Version: 2.1
Name: getpass-asterisk
Version: 1.0.1
Summary: An alternative implementation for getpass that echoes masked password (such as asterisks)
Home-page: https://github.com/secursive/getpass_asterisk
Author: Muhammad Akbar | Secursive
Author-email: akbar@secursive.com
License: UNKNOWN
Platform: UNKNOWN
Classifier: Programming Language :: Python :: 3
Classifier: License :: OSI Approved :: MIT License
Classifier: Operating System :: OS Independent
